{
  "channel_name": "Discovery Channel",
  "date": "2026-02-04",
  "programs": [
    {
      "show_name": "Bear Grylls: Escape From Hell  - Eps.3",
      "start_time": "00:35:00",
      "end_time": "01:30:00",
      "episode_number": ""
    },
    {
      "show_name": "Expedition Unknown  - Eps.1",
      "start_time": "01:30:00",
      "end_time": "02:25:00",
      "episode_number": ""
    },
    {
      "show_name": "Ghost Adventures  - Eps.1",
      "start_time": "02:25:00",
      "end_time": "03:20:00",
      "episode_number": ""
    },
    {
      "show_name": "Hoffman Family Gold  - Eps.3",
      "start_time": "03:20:00",
      "end_time": "04:10:00",
      "episode_number": ""
    },
    {
      "show_name": "Gold Rush: White Water  - Eps.11",
      "start_time": "04:10:00",
      "end_time": "05:00:00",
      "episode_number": ""
    },
    {
      "show_name": "Outback Opal Hunters  - Eps.20",
      "start_time": "05:00:00",
      "end_time": "06:00:00",
      "episode_number": ""
    },
    {
      "show_name": "Harpoon Hunters  - Eps.7",
      "start_time": "06:00:00",
      "end_time": "06:50:00",
      "episode_number": ""
    },
    {
      "show_name": "Gold Rush: White Water  - Eps.7",
      "start_time": "06:50:00",
      "end_time": "07:40:00",
      "episode_number": ""
    },
    {
      "show_name": "Jeremy Wade's Dark Waters  - Eps.8",
      "start_time": "07:40:00",
      "end_time": "08:30:00",
      "episode_number": ""
    },
    {
      "show_name": "Expedition Unknown  - Eps.1",
      "start_time": "08:30:00",
      "end_time": "09:20:00",
      "episode_number": ""
    },
    {
      "show_name": "Hoffman Family Gold  - Eps.4",
      "start_time": "09:20:00",
      "end_time": "10:10:00",
      "episode_number": ""
    },
    {
      "show_name": "Harpoon Hunters  - Eps.7",
      "start_time": "10:10:00",
      "end_time": "11:00:00",
      "episode_number": ""
    },
    {
      "show_name": "Gold Rush: White Water  - Eps.11",
      "start_time": "11:00:00",
      "end_time": "11:50:00",
      "episode_number": ""
    },
    {
      "show_name": "Mud Madness  - Eps.5",
      "start_time": "11:50:00",
      "end_time": "12:40:00",
      "episode_number": ""
    },
    {
      "show_name": "Wheeler Dealers World Tour  - Eps.1",
      "start_time": "12:40:00",
      "end_time": "13:35:00",
      "episode_number": ""
    },
    {
      "show_name": "Mike Brewer: Born Dealer  - Eps.6",
      "start_time": "13:35:00",
      "end_time": "14:30:00",
      "episode_number": ""
    },
    {
      "show_name": "Kindig Customs  - Eps.2",
      "start_time": "14:30:00",
      "end_time": "15:25:00",
      "episode_number": ""
    },
    {
      "show_name": "Kevin Hart's Muscle Car Crew  - Eps.4",
      "start_time": "15:25:00",
      "end_time": "16:20:00",
      "episode_number": ""
    },
    {
      "show_name": "Wheeler Dealers World Tour  - Eps.7",
      "start_time": "16:20:00",
      "end_time": "17:15:00",
      "episode_number": ""
    },
    {
      "show_name": "Gold Rush: White Water   - Eps.2",
      "start_time": "17:15:00",
      "end_time": "18:10:00",
      "episode_number": ""
    },
    {
      "show_name": "Kindig Customs  - Eps.10",
      "start_time": "18:10:00",
      "end_time": "19:05:00",
      "episode_number": ""
    },
    {
      "show_name": "High Speed Chase  - Eps.8",
      "start_time": "19:05:00",
      "end_time": "20:00:00",
      "episode_number": ""
    },
    {
      "show_name": "Wheeler Dealers World Tour  - Eps.2",
      "start_time": "20:00:00",
      "end_time": "20:55:00",
      "episode_number": ""
    },
    {
      "show_name": "Wheeler Dealers World Tour  - Eps.1",
      "start_time": "20:55:00",
      "end_time": "21:50:00",
      "episode_number": ""
    },
    {
      "show_name": "Mud Madness  - Eps.6",
      "start_time": "21:50:00",
      "end_time": "22:45:00",
      "episode_number": ""
    },
    {
      "show_name": "Kindig Customs  - Eps.10",
      "start_time": "22:45:00",
      "end_time": "23:40:00",
      "episode_number": ""
    },
    {
      "show_name": "Wheeler Dealers World Tour  - Eps.2",
      "start_time": "23:40:00",
      "end_time": "00:35:00",
      "episode_number": ""
    }
  ]
}